{
  "version": 3,
  "middleware": {
    "/": {
      "files": [
        "server/edge-runtime-webpack.js",
        "server/middleware.js"
      ],
      "name": "middleware",
      "page": "/",
      "matchers": [
        {
          "regexp": "^(?:\\/(_next\\/data\\/[^/]{1,}))?(?:\\/((?!_next\\/static|_next\\/image|favicon.ico).*))(\\.json)?[\\/#\\?]?$",
          "originalSource": "/((?!_next/static|_next/image|favicon.ico).*)"
        }
      ],
      "wasm": [],
      "assets": [],
      "env": {
        "__NEXT_BUILD_ID": "X-RojQpTpYI8PVOqVT2mH",
        "NEXT_SERVER_ACTIONS_ENCRYPTION_KEY": "dcGHYSLgtxS/k4v524ekXHboEGvCX/IEzZTJaPPMyuc=",
        "__NEXT_PREVIEW_MODE_ID": "c1fb7f2d893d4c2e7810127f84977f21",
        "__NEXT_PREVIEW_MODE_SIGNING_KEY": "96034cc4cf393cc021ce4608b5147eaa19bde72a2524d74d2f96f2d6d11333ba",
        "__NEXT_PREVIEW_MODE_ENCRYPTION_KEY": "dc26013a1e1de6ef487c4ae94a7b1bebeeb304e64957645d41e7c5f452c5b865"
      }
    }
  },
  "functions": {},
  "sortedMiddleware": [
    "/"
  ]
}